roboco/__init__.py
roboco/__main__.py
roboco/configurations.py
roboco/template.py
roboco/run.py
roboco/templates/abb_yumi/Dockerfile.melodic
roboco/templates/abb_yumi/Dockerfile.noetic
roboco/templates/baxter/Dockerfile.kinetic
roboco/templates/baxter/Dockerfile.noetic
roboco/templates/fetch/Dockerfile.noetic
roboco/templates/jackal/Dockerfile.foxy
roboco/templates/jackal/Dockerfile.humble
roboco/templates/jackal/Dockerfile.noetic
roboco/templates/panda/Dockerfile.noetic
roboco/templates/ridgeback/Dockerfile.noetic
roboco/templates/ros/Dockerfile.foxy
roboco/templates/ros/Dockerfile.galactic
roboco/templates/ros/Dockerfile.humble
roboco/templates/ros/Dockerfile.kinetic
roboco/templates/ros/Dockerfile.melodic
roboco/templates/ros/Dockerfile.noetic
roboco/templates/ur5/Dockerfile.humble
roboco/templates/ur5/Dockerfile.noetic
roboco-0.0.4.dist-info/METADATA
roboco-0.0.4.dist-info/WHEEL
roboco-0.0.4.dist-info/entry_points.txt
roboco-0.0.4.dist-info/licenses/LICENSE
roboco-0.0.4.dist-info/RECORD
