Metadata-Version: 2.1
Name: roboco
Version: 0.0.4
Summary: A tool to generate Dockerfiles for use in robotics, as well as a script to build and enter these containers, with support for graphical applications, GPU passthrough, realtime scheduling, host networking and full device access.
Project-URL: Documentation, https://github.com/monashrobotics/robot_containers#readme
Project-URL: Issues, https://github.com/monashrobotics/robot_containers/issues
Project-URL: Source, https://github.com/monashrobotics/robot_containers
Author-email: Owen Brooks <owen.h.brooks@gmail.com>
License-Expression: MIT
License-File: LICENSE
Keywords: containers,robotics
Classifier: Development Status :: 4 - Beta
Classifier: Programming Language :: Python
Classifier: Programming Language :: Python :: 3.7
Classifier: Programming Language :: Python :: 3.8
Classifier: Programming Language :: Python :: 3.9
Classifier: Programming Language :: Python :: 3.10
Classifier: Programming Language :: Python :: 3.11
Classifier: Programming Language :: Python :: Implementation :: CPython
Classifier: Programming Language :: Python :: Implementation :: PyPy
Requires-Python: >=3.7
Requires-Dist: importlib-resources==3.0.0; python_version < '3.9'
Requires-Dist: inquirerpy~=0.3.4
Requires-Dist: typing-extensions~=4.6.2
